pylibmagic/libmagic.so
pylibmagic/libmagic.so.1
pylibmagic/libmagic.la
pylibmagic/libmagic.so.1.0.0
pylibmagic/magic.mgc
pylibmagic/py.typed
pylibmagic/_version.py
pylibmagic/__init__.py
pylibmagic/_version.pyi
pylibmagic/pkgconfig/libmagic.pc
pylibmagic-0.5.0.dist-info/RECORD
pylibmagic-0.5.0.dist-info/entry_points.txt
pylibmagic-0.5.0.dist-info/WHEEL
pylibmagic-0.5.0.dist-info/METADATA
pylibmagic-0.5.0.dist-info/licenses/LICENSE
