Metadata-Version: 2.1
Name: pylibmagic
Version: 0.5.0
Summary: scikit-build project with CMake for compiling libmagic
Author-Email: Giordon Stark <kratsg@gmail.com>
Classifier: Development Status :: 4 - Beta
Classifier: Intended Audience :: Developers
Classifier: Intended Audience :: Science/Research
Classifier: License :: OSI Approved :: BSD License
Classifier: Operating System :: OS Independent
Classifier: Programming Language :: Python
Classifier: Programming Language :: Python :: 3
Classifier: Programming Language :: Python :: 3 :: Only
Classifier: Programming Language :: Python :: 3.7
Classifier: Programming Language :: Python :: 3.8
Classifier: Programming Language :: Python :: 3.9
Classifier: Programming Language :: Python :: 3.10
Classifier: Programming Language :: Python :: 3.11
Classifier: Programming Language :: Python :: 3.12
Classifier: Topic :: Scientific/Engineering
Project-URL: Bug tracker, https://github.com/kratsg/pylibmagic/issues
Project-URL: Changelog, https://github.com/kratsg/pylibmagic/releases
Project-URL: Discussions, https://github.com/kratsg/pylibmagic/discussions
Project-URL: Documentation, https://pylibmagic.readthedocs.io/
Project-URL: Homepage, https://github.com/kratsg/pylibmagic
Requires-Python: >=3.7
Requires-Dist: importlib-resources; python_version < "3.9"
Requires-Dist: typing-extensions>=3.7; python_version < "3.8"
Requires-Dist: pytest-cov>=3; extra == "dev"
Requires-Dist: pytest>=6; extra == "dev"
Requires-Dist: tbump>=6.7.0; extra == "dev"
Requires-Dist: twine; extra == "dev"
Requires-Dist: myst-parser>=0.13; extra == "docs"
Requires-Dist: sphinx-book-theme>=0.1.0; extra == "docs"
Requires-Dist: sphinx-copybutton; extra == "docs"
Requires-Dist: Sphinx>=4.0; extra == "docs"
Requires-Dist: pytest-cov>=3; extra == "test"
Requires-Dist: pytest>=6; extra == "test"
Requires-Dist: python-magic; extra == "test"
Provides-Extra: dev
Provides-Extra: docs
Provides-Extra: test
